{
  "name": "RobloxTycoon",
  "tree": {
    "$className": "DataModel",

    "ReplicatedFirst": {
      "$className": "ReplicatedFirst",
      "$path": "src/ReplicatedFirst"
    },

    "ReplicatedStorage": {
      "$className": "ReplicatedStorage",
      "$path": "src/ReplicatedStorage",
      "$ignoreUnknownInstances": true
    },

    "ServerScriptService": {
      "$className": "ServerScriptService",
      "$path": "src/ServerScriptService"
    },

    "StarterPlayer": {
      "$className": "StarterPlayer",
      "StarterCharacterScripts": {
        "$className": "StarterCharacterScripts",
        "$path": "src/StarterCharacterScripts"
      },
      "StarterPlayerScripts": {
        "$className": "StarterPlayerScripts",
        "$path": "src/StarterPlayerScripts"
      }
    },

    "StarterPack": {
      "AxeTool": {
        "$path": "src/Tools/AxeTool"
      }
    },

    "ServerStorage": {
      "$className": "ServerStorage",
      "TycoonTemplates": {
        "$className": "Folder",
        "$ignoreUnknownInstances": true
      }
    }
  }
}
